nonebot_plugin_setu4/__init__.py
nonebot_plugin_setu4/config.py
nonebot_plugin_setu4/fetch_resources.py
nonebot_plugin_setu4/get_data.py
nonebot_plugin_setu4/mamager_handle.py
nonebot_plugin_setu4/permission_manager.py
nonebot_plugin_setu4/send_setu.py
nonebot_plugin_setu4/setu_message.py
nonebot_plugin_setu4/resource/lolicon.db
nonebot_plugin_setu4-0.15.114514.1.dist-info/LICENSE
nonebot_plugin_setu4-0.15.114514.1.dist-info/METADATA
nonebot_plugin_setu4-0.15.114514.1.dist-info/WHEEL
nonebot_plugin_setu4-0.15.114514.1.dist-info/top_level.txt
nonebot_plugin_setu4-0.15.114514.1.dist-info/RECORD
