Metadata-Version: 2.1
Name: nonebot-plugin-setu4
Version: 0.15.114514.1
Summary: 内置数据库的setu插件, 尝试降低因为风控发不出图的概率
Home-page: https://github.com/Special-Week/nonebot_plugin_setu4
Author: Special-Week
Author-email: HuaMing27499@gmail.com
Requires-Python: >=3.9.0
License-File: LICENSE
Requires-Dist: pillow >=9.1.1
Requires-Dist: nonebot2
Requires-Dist: nonebot-adapter-onebot
Requires-Dist: httpx
